12/9/2025/problem_6.v
module circuit (
    input A, B, C,
    output F1, F2
);
    // Internal wires
    wire T1, T2, T3, F2_not;
    wire AB, AC, BC;

    // Top part (for F1)
    and  G1 (T1, A, B, C);        // T1 = A & B & C
    and  G2 (T2, A, B, C);        // T2 = A & B & C
    and  G6 (AB, A, B);
    and  G7 (AC, A, C);
    and  G8 (BC, B, C);
    or   G9 (F2, AB, AC, BC);     // F2 = AB | AC | BC
    not  G3 (F2_not, F2);
    and  G4 (T3, F2_not, T1);     // T3 = (~F2) & T1
    or   G5 (F1, T2, T3);         // F1 = T2 | T3

endmodule

12/9/2025/problem_6tb.v
module tb_circuit;
    reg A, B, C;
    wire F1, F2;

    circuit DUT (
        .A(A),
        .B(B),
        .C(C),
        .F1(F1),
        .F2(F2)
    );

    initial begin
        $dumpfile("problem_6.vcd");
        $dumpvars(0, tb_circuit);

        A=0; B=0; C=0; #10;
        A=0; B=0; C=1; #10;
        A=0; B=1; C=0; #10;
        A=0; B=1; C=1; #10;
        A=1; B=0; C=0; #10;
        A=1; B=0; C=1; #10;
        A=1; B=1; C=0; #10;
        A=1; B=1; C=1; #10;

        $finish;
    end
endmodule

12/9/2025/problem_6.vcd
$date
	Thu Sep 18 07:17:42 2025
$end
$version
	Icarus Verilog
$end
$timescale
	1s
$end
$scope module tb_circuit $end
$var wire 1 ! F2 $end
$var wire 1 " F1 $end
$var reg 1 # A $end
$var reg 1 $ B $end
$var reg 1 % C $end
$scope module DUT $end
$var wire 1 # A $end
$var wire 1 & AB $end
$var wire 1 ' AC $end
$var wire 1 $ B $end
$var wire 1 ( BC $end
$var wire 1 % C $end
$var wire 1 " F1 $end
$var wire 1 ! F2 $end
$var wire 1 ) F2_not $end
$var wire 1 * T1 $end
$var wire 1 + T2 $end
$var wire 1 , T3 $end
$upscope $end
$upscope $end
$enddefinitions $end
$comment Show the parameter values. $end
$dumpall
$end
#0
$dumpvars
0,
0+
0*
1)
0(
0'
0&
0%
0$
0#
0"
0!
$end
#10
1%
#20
0%
1$
#30
0)
1!
1(
1%
#40
1)
0!
0(
0%
0$
1#
#50
0)
1!
1'
1%
#60
0'
1&
0%
1$
#70
1"
1*
1+
1'
1(
1%
